{
    "Symbol": "MO",
    "AssetType": "Common Stock",
    "Name": "Altria Group",
    "Description": "Altria Group, Inc. (previously known as Philip Morris Companies, Inc.) is an American corporation and one of the world's largest producers and marketers of tobacco, cigarettes and related products. It operates worldwide and is headquartered in unincorporated Henrico County, Virginia, just outside the city of Richmond.",
    "CIK": "764180",
    "Exchange": "NYSE",
    "Currency": "USD",
    "Country": "USA",
    "Sector": "MANUFACTURING",
    "Industry": "CIGARETTES",
    "Address": "6601 WEST BROAD STREET, RICHMOND, VA, US",
    "FiscalYearEnd": "December",
    "LatestQuarter": "2023-03-31",
    "MarketCapitalization": "80969390000",
    "EBITDA": "12543000000",
    "PERatio": "13.92",
    "PEGRatio": "6.31",
    "BookValue": "-2.17",
    "DividendPerShare": "3.72",
    "DividendYield": "0.0843",
    "EPS": "3.112",
    "RevenuePerShareTTM": "11.49",
    "ProfitMargin": "0.271",
    "OperatingMarginTTM": "0.597",
    "ReturnOnAssetsTTM": "0.2",
    "ReturnOnEquityTTM": "0",
    "RevenueTTM": "20632001000",
    "GrossProfitTTM": "14183000000",
    "DilutedEPSTTM": "3.16",
    "QuarterlyEarningsGrowthYOY": "-0.071",
    "QuarterlyRevenueGrowthYOY": "-0.012",
    "AnalystTargetPrice": "49.21",
    "TrailingPE": "14.35",
    "ForwardPE": "9.51",
    "PriceToSalesRatioTTM": "4.067",
    "PriceToBookRatio": "27.3",
    "EVToRevenue": "5.23",
    "EVToEBITDA": "12.99",
    "Beta": "0.626",
    "52WeekHigh": "48.04",
    "52WeekLow": "38.47",
    "50DayMovingAverage": "45.5",
    "200DayMovingAverage": "45.34",
    "SharesOutstanding": "1785040000",
    "DividendDate": "2023-07-10",
    "ExDividendDate": "2023-06-14"
}