{
    "symbol": "DEO",
    "annualReports": [
        {
            "fiscalDateEnding": "2022-06-30",
            "reportedCurrency": "GBP",
            "totalAssets": "36516000000",
            "totalCurrentAssets": "12934000000",
            "cashAndCashEquivalentsAtCarryingValue": "2285000000",
            "cashAndShortTermInvestments": "2285000000",
            "inventory": "7094000000",
            "currentNetReceivables": "None",
            "totalNonCurrentAssets": "23582000000",
            "propertyPlantEquipment": "5848000000",
            "accumulatedDepreciationAmortizationPPE": "None",
            "intangibleAssets": "9615000000",
            "intangibleAssetsExcludingGoodwill": "9615000000",
            "goodwill": "2287000000",
            "investments": "None",
            "longTermInvestments": "None",
            "shortTermInvestments": "251000000",
            "otherCurrentAssets": "3304000000",
            "otherNonCurrentAssets": "None",
            "totalLiabilities": "27002000000",
            "totalCurrentLiabilities": "8442000000",
            "currentAccountsPayable": "None",
            "deferredRevenue": "None",
            "currentDebt": "None",
            "shortTermDebt": "1522000000",
            "totalNonCurrentLiabilities": "18560000000",
            "capitalLeaseObligations": "475000000",
            "longTermDebt": "14498000000",
            "currentLongTermDebt": "1522000000",
            "longTermDebtNoncurrent": "None",
            "shortLongTermDebtTotal": "16020000000",
            "otherCurrentLiabilities": "1033000000",
            "otherNonCurrentLiabilities": "None",
            "totalShareholderEquity": "7798000000",
            "treasuryStock": "None",
            "retainedEarnings": "5388000000",
            "commonStock": "723000000",
            "commonStockSharesOutstanding": "581250000"
        },
        {
            "fiscalDateEnding": "2021-06-30",
            "reportedCurrency": "GBP",
            "totalAssets": "31953000000",
            "totalCurrentAssets": "11445000000",
            "cashAndCashEquivalentsAtCarryingValue": "2749000000",
            "cashAndShortTermInvestments": "2749000000",
            "inventory": "6045000000",
            "currentNetReceivables": "None",
            "totalNonCurrentAssets": "20508000000",
            "propertyPlantEquipment": "4849000000",
            "accumulatedDepreciationAmortizationPPE": "None",
            "intangibleAssets": "8807000000",
            "intangibleAssetsExcludingGoodwill": "8807000000",
            "goodwill": "1957000000",
            "investments": "None",
            "longTermInvestments": "None",
            "shortTermInvestments": "121000000",
            "otherCurrentAssets": "2605000000",
            "otherNonCurrentAssets": "None",
            "totalLiabilities": "23522000000",
            "totalCurrentLiabilities": "7142000000",
            "currentAccountsPayable": "None",
            "deferredRevenue": "None",
            "currentDebt": "None",
            "shortTermDebt": "1862000000",
            "totalNonCurrentLiabilities": "16380000000",
            "capitalLeaseObligations": "363000000",
            "longTermDebt": "12865000000",
            "currentLongTermDebt": "1862000000",
            "longTermDebtNoncurrent": "None",
            "shortLongTermDebtTotal": "14727000000",
            "otherCurrentLiabilities": "632000000",
            "otherNonCurrentLiabilities": "None",
            "totalShareholderEquity": "6897000000",
            "treasuryStock": "-1877000000",
            "retainedEarnings": "5061000000",
            "commonStock": "741000000",
            "commonStockSharesOutstanding": "586250000"
        },
        {
            "fiscalDateEnding": "2020-06-30",
            "reportedCurrency": "USD",
            "totalAssets": "33308000000",
            "totalCurrentAssets": "11471000000",
            "cashAndCashEquivalentsAtCarryingValue": "3323000000",
            "cashAndShortTermInvestments": "3323000000",
            "inventory": "5772000000",
            "currentNetReceivables": "None",
            "totalNonCurrentAssets": "21837000000",
            "propertyPlantEquipment": "4926000000",
            "accumulatedDepreciationAmortizationPPE": "None",
            "intangibleAssets": "9388000000",
            "intangibleAssetsExcludingGoodwill": "9388000000",
            "goodwill": "1912000000",
            "investments": "None",
            "longTermInvestments": "None",
            "shortTermInvestments": "75000000",
            "otherCurrentAssets": "2303000000",
            "otherNonCurrentAssets": "None",
            "totalLiabilities": "24868000000",
            "totalCurrentLiabilities": "6496000000",
            "currentAccountsPayable": "None",
            "deferredRevenue": "None",
            "currentDebt": "None",
            "shortTermDebt": "1995000000",
            "totalNonCurrentLiabilities": "18372000000",
            "capitalLeaseObligations": "470000000",
            "longTermDebt": "14790000000",
            "currentLongTermDebt": "1995000000",
            "longTermDebtNoncurrent": "None",
            "shortLongTermDebtTotal": "16785000000",
            "otherCurrentLiabilities": "818000000",
            "otherNonCurrentLiabilities": "None",
            "totalShareholderEquity": "6772000000",
            "treasuryStock": "-1936000000",
            "retainedEarnings": "4343000000",
            "commonStock": "742000000",
            "commonStockSharesOutstanding": "588500000"
        },
        {
            "fiscalDateEnding": "2019-06-30",
            "reportedCurrency": "USD",
            "totalAssets": "31296000000",
            "totalCurrentAssets": "9373000000",
            "cashAndCashEquivalentsAtCarryingValue": "932000000",
            "cashAndShortTermInvestments": "932000000",
            "inventory": "5472000000",
            "currentNetReceivables": "None",
            "totalNonCurrentAssets": "21923000000",
            "propertyPlantEquipment": "4455000000",
            "accumulatedDepreciationAmortizationPPE": "0",
            "intangibleAssets": "9875000000",
            "intangibleAssetsExcludingGoodwill": "9875000000",
            "goodwill": "2682000000",
            "investments": "None",
            "longTermInvestments": "53857189704.85",
            "shortTermInvestments": "127000000",
            "otherCurrentAssets": "2845000000",
            "otherNonCurrentAssets": "None",
            "totalLiabilities": "21140000000",
            "totalCurrentLiabilities": "7003000000",
            "currentAccountsPayable": "None",
            "deferredRevenue": "None",
            "currentDebt": "None",
            "shortTermDebt": "1959000000",
            "totalNonCurrentLiabilities": "14137000000",
            "capitalLeaseObligations": "128000000",
            "longTermDebt": "10596000000",
            "currentLongTermDebt": "1959000000",
            "longTermDebtNoncurrent": "None",
            "shortLongTermDebtTotal": "12555000000",
            "otherCurrentLiabilities": "842000000",
            "otherNonCurrentLiabilities": "0",
            "totalShareholderEquity": "8361000000",
            "treasuryStock": "-2026000000",
            "retainedEarnings": "3886000000",
            "commonStock": "753000000",
            "commonStockSharesOutstanding": "607000000"
        },
        {
            "fiscalDateEnding": "2018-06-30",
            "reportedCurrency": "USD",
            "totalAssets": "29715000000",
            "totalCurrentAssets": "8691000000",
            "cashAndCashEquivalentsAtCarryingValue": "874000000",
            "cashAndShortTermInvestments": "874000000",
            "inventory": "5015000000",
            "currentNetReceivables": "None",
            "totalNonCurrentAssets": "21024000000",
            "propertyPlantEquipment": "4089000000",
            "accumulatedDepreciationAmortizationPPE": "0",
            "intangibleAssets": "9894000000",
            "intangibleAssetsExcludingGoodwill": "9894000000",
            "goodwill": "2678000000",
            "investments": "None",
            "longTermInvestments": "81509338067.21",
            "shortTermInvestments": "25000000",
            "otherCurrentAssets": "2777000000",
            "otherNonCurrentAssets": "None",
            "totalLiabilities": "18002000000",
            "totalCurrentLiabilities": "6360000000",
            "currentAccountsPayable": "None",
            "deferredRevenue": "None",
            "currentDebt": "None",
            "shortTermDebt": "1859000000",
            "totalNonCurrentLiabilities": "11642000000",
            "capitalLeaseObligations": "155000000",
            "longTermDebt": "8074000000",
            "currentLongTermDebt": "1828000000",
            "longTermDebtNoncurrent": "None",
            "shortLongTermDebtTotal": "10057000000",
            "otherCurrentLiabilities": "2106000000",
            "otherNonCurrentLiabilities": "0",
            "totalShareholderEquity": "9948000000",
            "treasuryStock": "-2144000000",
            "retainedEarnings": "5686000000",
            "commonStock": "780000000",
            "commonStockSharesOutstanding": "623750000"
        }
    ],
    "quarterlyReports": [
        {
            "fiscalDateEnding": "2022-12-31",
            "reportedCurrency": "GBP",
            "totalAssets": "38719000000",
            "totalCurrentAssets": "14938000000",
            "cashAndCashEquivalentsAtCarryingValue": "2766000000",
            "cashAndShortTermInvestments": "2766000000",
            "inventory": "7552000000",
            "currentNetReceivables": "None",
            "totalNonCurrentAssets": "23781000000",
            "propertyPlantEquipment": "6091000000",
            "accumulatedDepreciationAmortizationPPE": "None",
            "intangibleAssets": "12130000000",
            "intangibleAssetsExcludingGoodwill": "12130000000",
            "goodwill": "None",
            "investments": "None",
            "longTermInvestments": "None",
            "shortTermInvestments": "398000000",
            "otherCurrentAssets": "4222000000",
            "otherNonCurrentAssets": "None",
            "totalLiabilities": "28853000000",
            "totalCurrentLiabilities": "9521000000",
            "currentAccountsPayable": "None",
            "deferredRevenue": "None",
            "currentDebt": "None",
            "shortTermDebt": "2305000000",
            "totalNonCurrentLiabilities": "19332000000",
            "capitalLeaseObligations": "None",
            "longTermDebt": "15304000000",
            "currentLongTermDebt": "2305000000",
            "longTermDebtNoncurrent": "None",
            "shortLongTermDebtTotal": "17609000000",
            "otherCurrentLiabilities": "1106000000",
            "otherNonCurrentLiabilities": "None",
            "totalShareholderEquity": "8139000000",
            "treasuryStock": "None",
            "retainedEarnings": "5697000000",
            "commonStock": "719000000",
            "commonStockSharesOutstanding": "2269610939"
        },
        {
            "fiscalDateEnding": "2022-06-30",
            "reportedCurrency": "GBP",
            "totalAssets": "36516000000",
            "totalCurrentAssets": "12934000000",
            "cashAndCashEquivalentsAtCarryingValue": "2285000000",
            "cashAndShortTermInvestments": "2285000000",
            "inventory": "7094000000",
            "currentNetReceivables": "None",
            "totalNonCurrentAssets": "23582000000",
            "propertyPlantEquipment": "5848000000",
            "accumulatedDepreciationAmortizationPPE": "None",
            "intangibleAssets": "9615000000",
            "intangibleAssetsExcludingGoodwill": "9615000000",
            "goodwill": "2287000000",
            "investments": "None",
            "longTermInvestments": "None",
            "shortTermInvestments": "251000000",
            "otherCurrentAssets": "3304000000",
            "otherNonCurrentAssets": "None",
            "totalLiabilities": "27002000000",
            "totalCurrentLiabilities": "8442000000",
            "currentAccountsPayable": "None",
            "deferredRevenue": "None",
            "currentDebt": "None",
            "shortTermDebt": "1522000000",
            "totalNonCurrentLiabilities": "18560000000",
            "capitalLeaseObligations": "475000000",
            "longTermDebt": "14498000000",
            "currentLongTermDebt": "1522000000",
            "longTermDebtNoncurrent": "None",
            "shortLongTermDebtTotal": "16020000000",
            "otherCurrentLiabilities": "1033000000",
            "otherNonCurrentLiabilities": "None",
            "totalShareholderEquity": "7798000000",
            "treasuryStock": "None",
            "retainedEarnings": "5388000000",
            "commonStock": "723000000",
            "commonStockSharesOutstanding": "2280746113"
        },
        {
            "fiscalDateEnding": "2022-03-31",
            "reportedCurrency": "GBP",
            "totalAssets": "None",
            "totalCurrentAssets": "12934000000",
            "cashAndCashEquivalentsAtCarryingValue": "None",
            "cashAndShortTermInvestments": "None",
            "inventory": "7094000000",
            "currentNetReceivables": "None",
            "totalNonCurrentAssets": "None",
            "propertyPlantEquipment": "5848000000",
            "accumulatedDepreciationAmortizationPPE": "None",
            "intangibleAssets": "None",
            "intangibleAssetsExcludingGoodwill": "None",
            "goodwill": "None",
            "investments": "None",
            "longTermInvestments": "None",
            "shortTermInvestments": "None",
            "otherCurrentAssets": "337000000",
            "otherNonCurrentAssets": "None",
            "totalLiabilities": "None",
            "totalCurrentLiabilities": "8442000000",
            "currentAccountsPayable": "None",
            "deferredRevenue": "None",
            "currentDebt": "None",
            "shortTermDebt": "None",
            "totalNonCurrentLiabilities": "None",
            "capitalLeaseObligations": "None",
            "longTermDebt": "None",
            "currentLongTermDebt": "None",
            "longTermDebtNoncurrent": "None",
            "shortLongTermDebtTotal": "None",
            "otherCurrentLiabilities": "1655000000",
            "otherNonCurrentLiabilities": "None",
            "totalShareholderEquity": "None",
            "treasuryStock": "None",
            "retainedEarnings": "5388000000",
            "commonStock": "723000000",
            "commonStockSharesOutstanding": "None"
        },
        {
            "fiscalDateEnding": "2021-12-31",
            "reportedCurrency": "GBP",
            "totalAssets": "33160000000",
            "totalCurrentAssets": "11576000000",
            "cashAndCashEquivalentsAtCarryingValue": "1780000000",
            "cashAndShortTermInvestments": "1780000000",
            "inventory": "6235000000",
            "currentNetReceivables": "None",
            "totalNonCurrentAssets": "21584000000",
            "propertyPlantEquipment": "5091000000",
            "accumulatedDepreciationAmortizationPPE": "None",
            "intangibleAssets": "10921000000",
            "intangibleAssetsExcludingGoodwill": "10921000000",
            "goodwill": "None",
            "investments": "None",
            "longTermInvestments": "None",
            "shortTermInvestments": "66000000",
            "otherCurrentAssets": "3495000000",
            "otherNonCurrentAssets": "None",
            "totalLiabilities": "23829000000",
            "totalCurrentLiabilities": "7604000000",
            "currentAccountsPayable": "None",
            "deferredRevenue": "None",
            "currentDebt": "None",
            "shortTermDebt": "1184000000",
            "totalNonCurrentLiabilities": "16225000000",
            "capitalLeaseObligations": "None",
            "longTermDebt": "12693000000",
            "currentLongTermDebt": "None",
            "longTermDebtNoncurrent": "None",
            "shortLongTermDebtTotal": "13877000000",
            "otherCurrentLiabilities": "1093000000",
            "otherNonCurrentLiabilities": "None",
            "totalShareholderEquity": "7658000000",
            "treasuryStock": "None",
            "retainedEarnings": "5866000000",
            "commonStock": "737000000",
            "commonStockSharesOutstanding": "2326780744"
        },
        {
            "fiscalDateEnding": "2021-09-30",
            "reportedCurrency": "GBP",
            "totalAssets": "None",
            "totalCurrentAssets": "11576000000",
            "cashAndCashEquivalentsAtCarryingValue": "None",
            "cashAndShortTermInvestments": "None",
            "inventory": "6235000000",
            "currentNetReceivables": "None",
            "totalNonCurrentAssets": "None",
            "propertyPlantEquipment": "5091000000",
            "accumulatedDepreciationAmortizationPPE": "None",
            "intangibleAssets": "None",
            "intangibleAssetsExcludingGoodwill": "None",
            "goodwill": "None",
            "investments": "None",
            "longTermInvestments": "None",
            "shortTermInvestments": "None",
            "otherCurrentAssets": "82000000",
            "otherNonCurrentAssets": "None",
            "totalLiabilities": "None",
            "totalCurrentLiabilities": "7604000000",
            "currentAccountsPayable": "None",
            "deferredRevenue": "None",
            "currentDebt": "None",
            "shortTermDebt": "None",
            "totalNonCurrentLiabilities": "None",
            "capitalLeaseObligations": "None",
            "longTermDebt": "None",
            "currentLongTermDebt": "None",
            "longTermDebtNoncurrent": "None",
            "shortLongTermDebtTotal": "None",
            "otherCurrentLiabilities": "1093000000",
            "otherNonCurrentLiabilities": "None",
            "totalShareholderEquity": "None",
            "treasuryStock": "None",
            "retainedEarnings": "5866000000",
            "commonStock": "737000000",
            "commonStockSharesOutstanding": "None"
        },
        {
            "fiscalDateEnding": "2021-06-30",
            "reportedCurrency": "GBP",
            "totalAssets": "31953000000",
            "totalCurrentAssets": "11445000000",
            "cashAndCashEquivalentsAtCarryingValue": "2749000000",
            "cashAndShortTermInvestments": "2749000000",
            "inventory": "6045000000",
            "currentNetReceivables": "None",
            "totalNonCurrentAssets": "20508000000",
            "propertyPlantEquipment": "4849000000",
            "accumulatedDepreciationAmortizationPPE": "None",
            "intangibleAssets": "8807000000",
            "intangibleAssetsExcludingGoodwill": "8807000000",
            "goodwill": "1957000000",
            "investments": "None",
            "longTermInvestments": "None",
            "shortTermInvestments": "46000000",
            "otherCurrentAssets": "2605000000",
            "otherNonCurrentAssets": "None",
            "totalLiabilities": "23522000000",
            "totalCurrentLiabilities": "7142000000",
            "currentAccountsPayable": "None",
            "deferredRevenue": "None",
            "currentDebt": "None",
            "shortTermDebt": "1944000000",
            "totalNonCurrentLiabilities": "16380000000",
            "capitalLeaseObligations": "363000000",
            "longTermDebt": "12865000000",
            "currentLongTermDebt": "1862000000",
            "longTermDebtNoncurrent": "None",
            "shortLongTermDebtTotal": "15090000000",
            "otherCurrentLiabilities": "2382000000",
            "otherNonCurrentLiabilities": "None",
            "totalShareholderEquity": "6897000000",
            "treasuryStock": "-1877000000",
            "retainedEarnings": "5061000000",
            "commonStock": "741000000",
            "commonStockSharesOutstanding": "2337927468"
        },
        {
            "fiscalDateEnding": "2021-03-31",
            "reportedCurrency": "GBP",
            "totalAssets": "None",
            "totalCurrentAssets": "11445000000",
            "cashAndCashEquivalentsAtCarryingValue": "None",
            "cashAndShortTermInvestments": "None",
            "inventory": "6045000000",
            "currentNetReceivables": "None",
            "totalNonCurrentAssets": "None",
            "propertyPlantEquipment": "4849000000",
            "accumulatedDepreciationAmortizationPPE": "None",
            "intangibleAssets": "None",
            "intangibleAssetsExcludingGoodwill": "None",
            "goodwill": "None",
            "investments": "None",
            "longTermInvestments": "None",
            "shortTermInvestments": "None",
            "otherCurrentAssets": "71000000",
            "otherNonCurrentAssets": "None",
            "totalLiabilities": "None",
            "totalCurrentLiabilities": "7142000000",
            "currentAccountsPayable": "None",
            "deferredRevenue": "None",
            "currentDebt": "None",
            "shortTermDebt": "None",
            "totalNonCurrentLiabilities": "None",
            "capitalLeaseObligations": "None",
            "longTermDebt": "None",
            "currentLongTermDebt": "None",
            "longTermDebtNoncurrent": "None",
            "shortLongTermDebtTotal": "None",
            "otherCurrentLiabilities": "1252000000",
            "otherNonCurrentLiabilities": "None",
            "totalShareholderEquity": "None",
            "treasuryStock": "None",
            "retainedEarnings": "5061000000",
            "commonStock": "741000000",
            "commonStockSharesOutstanding": "None"
        },
        {
            "fiscalDateEnding": "2020-12-31",
            "reportedCurrency": "USD",
            "totalAssets": "32804000000",
            "totalCurrentAssets": "11845000000",
            "cashAndCashEquivalentsAtCarryingValue": "2763000000",
            "cashAndShortTermInvestments": "2763000000",
            "inventory": "5750000000",
            "currentNetReceivables": "None",
            "totalNonCurrentAssets": "20959000000",
            "propertyPlantEquipment": "4757000000",
            "accumulatedDepreciationAmortizationPPE": "None",
            "intangibleAssets": "10877000000",
            "intangibleAssetsExcludingGoodwill": "10877000000",
            "goodwill": "None",
            "investments": "None",
            "longTermInvestments": "None",
            "shortTermInvestments": "84000000",
            "otherCurrentAssets": "3248000000",
            "otherNonCurrentAssets": "None",
            "totalLiabilities": "24426000000",
            "totalCurrentLiabilities": "6710000000",
            "currentAccountsPayable": "None",
            "deferredRevenue": "None",
            "currentDebt": "None",
            "shortTermDebt": "1214000000",
            "totalNonCurrentLiabilities": "17716000000",
            "capitalLeaseObligations": "None",
            "longTermDebt": "14063000000",
            "currentLongTermDebt": "None",
            "longTermDebtNoncurrent": "None",
            "shortLongTermDebtTotal": "15277000000",
            "otherCurrentLiabilities": "508000000",
            "otherNonCurrentLiabilities": "None",
            "totalShareholderEquity": "6818000000",
            "treasuryStock": "-1895000000",
            "retainedEarnings": "4785000000",
            "commonStock": "742000000",
            "commonStockSharesOutstanding": "721500000"
        },
        {
            "fiscalDateEnding": "2020-09-30",
            "reportedCurrency": "GBP",
            "totalAssets": "None",
            "totalCurrentAssets": "11845000000",
            "cashAndCashEquivalentsAtCarryingValue": "None",
            "cashAndShortTermInvestments": "None",
            "inventory": "5750000000",
            "currentNetReceivables": "None",
            "totalNonCurrentAssets": "None",
            "propertyPlantEquipment": "4757000000",
            "accumulatedDepreciationAmortizationPPE": "None",
            "intangibleAssets": "None",
            "intangibleAssetsExcludingGoodwill": "None",
            "goodwill": "None",
            "investments": "None",
            "longTermInvestments": "None",
            "shortTermInvestments": "None",
            "otherCurrentAssets": "84000000",
            "otherNonCurrentAssets": "None",
            "totalLiabilities": "None",
            "totalCurrentLiabilities": "6710000000",
            "currentAccountsPayable": "None",
            "deferredRevenue": "None",
            "currentDebt": "None",
            "shortTermDebt": "None",
            "totalNonCurrentLiabilities": "None",
            "capitalLeaseObligations": "None",
            "longTermDebt": "None",
            "currentLongTermDebt": "None",
            "longTermDebtNoncurrent": "None",
            "shortLongTermDebtTotal": "None",
            "otherCurrentLiabilities": "838000000",
            "otherNonCurrentLiabilities": "None",
            "totalShareholderEquity": "None",
            "treasuryStock": "None",
            "retainedEarnings": "4785000000",
            "commonStock": "742000000",
            "commonStockSharesOutstanding": "None"
        },
        {
            "fiscalDateEnding": "2020-06-30",
            "reportedCurrency": "USD",
            "totalAssets": "33308000000",
            "totalCurrentAssets": "11471000000",
            "cashAndCashEquivalentsAtCarryingValue": "3323000000",
            "cashAndShortTermInvestments": "3323000000",
            "inventory": "5772000000",
            "currentNetReceivables": "None",
            "totalNonCurrentAssets": "21837000000",
            "propertyPlantEquipment": "4926000000",
            "accumulatedDepreciationAmortizationPPE": "None",
            "intangibleAssets": "9388000000",
            "intangibleAssetsExcludingGoodwill": "9388000000",
            "goodwill": "1912000000",
            "investments": "None",
            "longTermInvestments": "None",
            "shortTermInvestments": "73000000",
            "otherCurrentAssets": "2303000000",
            "otherNonCurrentAssets": "None",
            "totalLiabilities": "24868000000",
            "totalCurrentLiabilities": "6496000000",
            "currentAccountsPayable": "None",
            "deferredRevenue": "None",
            "currentDebt": "None",
            "shortTermDebt": "2101000000",
            "totalNonCurrentLiabilities": "18372000000",
            "capitalLeaseObligations": "470000000",
            "longTermDebt": "14790000000",
            "currentLongTermDebt": "1995000000",
            "longTermDebtNoncurrent": "None",
            "shortLongTermDebtTotal": "17255000000",
            "otherCurrentLiabilities": "2118000000",
            "otherNonCurrentLiabilities": "None",
            "totalShareholderEquity": "6772000000",
            "treasuryStock": "-1936000000",
            "retainedEarnings": "4343000000",
            "commonStock": "742000000",
            "commonStockSharesOutstanding": "721500000"
        },
        {
            "fiscalDateEnding": "2020-03-31",
            "reportedCurrency": "GBP",
            "totalAssets": "None",
            "totalCurrentAssets": "11471000000",
            "cashAndCashEquivalentsAtCarryingValue": "None",
            "cashAndShortTermInvestments": "None",
            "inventory": "5772000000",
            "currentNetReceivables": "None",
            "totalNonCurrentAssets": "None",
            "propertyPlantEquipment": "4926000000",
            "accumulatedDepreciationAmortizationPPE": "None",
            "intangibleAssets": "None",
            "intangibleAssetsExcludingGoodwill": "None",
            "goodwill": "None",
            "investments": "None",
            "longTermInvestments": "None",
            "shortTermInvestments": "None",
            "otherCurrentAssets": "2000000",
            "otherNonCurrentAssets": "None",
            "totalLiabilities": "None",
            "totalCurrentLiabilities": "6496000000",
            "currentAccountsPayable": "None",
            "deferredRevenue": "None",
            "currentDebt": "None",
            "shortTermDebt": "None",
            "totalNonCurrentLiabilities": "None",
            "capitalLeaseObligations": "None",
            "longTermDebt": "None",
            "currentLongTermDebt": "None",
            "longTermDebtNoncurrent": "None",
            "shortLongTermDebtTotal": "None",
            "otherCurrentLiabilities": "1241000000",
            "otherNonCurrentLiabilities": "None",
            "totalShareholderEquity": "None",
            "treasuryStock": "None",
            "retainedEarnings": "4343000000",
            "commonStock": "742000000",
            "commonStockSharesOutstanding": "None"
        },
        {
            "fiscalDateEnding": "2019-12-31",
            "reportedCurrency": "USD",
            "totalAssets": "31733000000",
            "totalCurrentAssets": "10157000000",
            "cashAndCashEquivalentsAtCarryingValue": "950000000",
            "cashAndShortTermInvestments": "950000000",
            "inventory": "5459000000",
            "currentNetReceivables": "None",
            "totalNonCurrentAssets": "21576000000",
            "propertyPlantEquipment": "4834000000",
            "accumulatedDepreciationAmortizationPPE": "0",
            "intangibleAssets": "12035000000",
            "intangibleAssetsExcludingGoodwill": "12035000000",
            "goodwill": "0",
            "investments": "None",
            "longTermInvestments": "96960173927.97",
            "shortTermInvestments": "42000000",
            "otherCurrentAssets": "3706000000",
            "otherNonCurrentAssets": "None",
            "totalLiabilities": "22503000000",
            "totalCurrentLiabilities": "8853000000",
            "currentAccountsPayable": "None",
            "deferredRevenue": "None",
            "currentDebt": "None",
            "shortTermDebt": "3381000000",
            "totalNonCurrentLiabilities": "13650000000",
            "capitalLeaseObligations": "0",
            "longTermDebt": "10091000000",
            "currentLongTermDebt": "3381000000",
            "longTermDebtNoncurrent": "None",
            "shortLongTermDebtTotal": "13472000000",
            "otherCurrentLiabilities": "662000000",
            "otherNonCurrentLiabilities": "0",
            "totalShareholderEquity": "7523000000",
            "treasuryStock": "-1952000000",
            "retainedEarnings": "3499000000",
            "commonStock": "743000000",
            "commonStockSharesOutstanding": "2340778811"
        },
        {
            "fiscalDateEnding": "2019-09-30",
            "reportedCurrency": "GBP",
            "totalAssets": "377207094854.20",
            "totalCurrentAssets": "10157000000",
            "cashAndCashEquivalentsAtCarryingValue": "11292557908.64",
            "cashAndShortTermInvestments": "11292557908.64",
            "inventory": "5459000000",
            "currentNetReceivables": "None",
            "totalNonCurrentAssets": "0",
            "propertyPlantEquipment": "4834000000",
            "accumulatedDepreciationAmortizationPPE": "0",
            "intangibleAssets": "143058878346.44",
            "intangibleAssetsExcludingGoodwill": "143058878346.44",
            "goodwill": "0",
            "investments": "None",
            "longTermInvestments": "38668095659.44",
            "shortTermInvestments": "0",
            "otherCurrentAssets": "93000000",
            "otherNonCurrentAssets": "None",
            "totalLiabilities": "267490979595.49",
            "totalCurrentLiabilities": "8853000000",
            "currentAccountsPayable": "None",
            "deferredRevenue": "None",
            "currentDebt": "None",
            "shortTermDebt": "0",
            "totalNonCurrentLiabilities": "0",
            "capitalLeaseObligations": "0",
            "longTermDebt": "119950738794.74",
            "currentLongTermDebt": "38632434950.17",
            "longTermDebtNoncurrent": "None",
            "shortLongTermDebtTotal": "0",
            "otherCurrentLiabilities": "917000000",
            "otherNonCurrentLiabilities": "0",
            "totalShareholderEquity": "89425171732.51",
            "treasuryStock": "0",
            "retainedEarnings": "5451000000",
            "commonStock": "743000000",
            "commonStockSharesOutstanding": "21238814200"
        },
        {
            "fiscalDateEnding": "2019-06-30",
            "reportedCurrency": "USD",
            "totalAssets": "31296000000",
            "totalCurrentAssets": "9373000000",
            "cashAndCashEquivalentsAtCarryingValue": "932000000",
            "cashAndShortTermInvestments": "932000000",
            "inventory": "5472000000",
            "currentNetReceivables": "None",
            "totalNonCurrentAssets": "21923000000",
            "propertyPlantEquipment": "4489000000",
            "accumulatedDepreciationAmortizationPPE": "0",
            "intangibleAssets": "9875000000",
            "intangibleAssetsExcludingGoodwill": "9875000000",
            "goodwill": "2682000000",
            "investments": "None",
            "longTermInvestments": "53857189704.85",
            "shortTermInvestments": "124000000",
            "otherCurrentAssets": "2845000000",
            "otherNonCurrentAssets": "None",
            "totalLiabilities": "21140000000",
            "totalCurrentLiabilities": "7003000000",
            "currentAccountsPayable": "None",
            "deferredRevenue": "None",
            "currentDebt": "None",
            "shortTermDebt": "2002000000",
            "totalNonCurrentLiabilities": "14137000000",
            "capitalLeaseObligations": "128000000",
            "longTermDebt": "10596000000",
            "currentLongTermDebt": "1959000000",
            "longTermDebtNoncurrent": "None",
            "shortLongTermDebtTotal": "12683000000",
            "otherCurrentLiabilities": "2289000000",
            "otherNonCurrentLiabilities": "0",
            "totalShareholderEquity": "8361000000",
            "treasuryStock": "-2026000000",
            "retainedEarnings": "3886000000",
            "commonStock": "753000000",
            "commonStockSharesOutstanding": "2443756400"
        },
        {
            "fiscalDateEnding": "2019-03-31",
            "reportedCurrency": "GBP",
            "totalAssets": "800102605232.88",
            "totalCurrentAssets": "239626844288.63",
            "cashAndCashEquivalentsAtCarryingValue": "23827186479.97",
            "cashAndShortTermInvestments": "23827186479.97",
            "inventory": "139895240792.23",
            "currentNetReceivables": "None",
            "totalNonCurrentAssets": "0",
            "propertyPlantEquipment": "4455000000",
            "accumulatedDepreciationAmortizationPPE": "0",
            "intangibleAssets": "252460800954.74",
            "intangibleAssetsExcludingGoodwill": "252460800954.74",
            "goodwill": "68567075256.64",
            "investments": "None",
            "longTermInvestments": "82858274014.50",
            "shortTermInvestments": "3170140690.59",
            "otherCurrentAssets": "1738464249.68",
            "otherNonCurrentAssets": "None",
            "totalLiabilities": "540457856423.42",
            "totalCurrentLiabilities": "179036252059.36",
            "currentAccountsPayable": "None",
            "deferredRevenue": "None",
            "currentDebt": "None",
            "shortTermDebt": "0",
            "totalNonCurrentLiabilities": "0",
            "capitalLeaseObligations": "0",
            "longTermDebt": "271200422939.34",
            "currentLongTermDebt": "25028772064.04",
            "longTermDebtNoncurrent": "None",
            "shortLongTermDebtTotal": "0",
            "otherCurrentLiabilities": "36891234002.88",
            "otherNonCurrentLiabilities": "0",
            "totalShareholderEquity": "213754405750.18",
            "treasuryStock": "0",
            "retainedEarnings": "5912000000",
            "commonStock": "753000000",
            "commonStockSharesOutstanding": "48462584800"
        },
        {
            "fiscalDateEnding": "2018-12-31",
            "reportedCurrency": "USD",
            "totalAssets": "32094000000",
            "totalCurrentAssets": "10515000000",
            "cashAndCashEquivalentsAtCarryingValue": "1591000000",
            "cashAndShortTermInvestments": "1591000000",
            "inventory": "5276000000",
            "currentNetReceivables": "None",
            "totalNonCurrentAssets": "21579000000",
            "propertyPlantEquipment": "4264000000",
            "accumulatedDepreciationAmortizationPPE": "0",
            "intangibleAssets": "12555000000",
            "intangibleAssetsExcludingGoodwill": "12555000000",
            "goodwill": "0",
            "investments": "None",
            "longTermInvestments": "8685361768.14",
            "shortTermInvestments": "12000000",
            "otherCurrentAssets": "3636000000",
            "otherNonCurrentAssets": "None",
            "totalLiabilities": "20961000000",
            "totalCurrentLiabilities": "7128000000",
            "currentAccountsPayable": "None",
            "deferredRevenue": "None",
            "currentDebt": "None",
            "shortTermDebt": "1742000000",
            "totalNonCurrentLiabilities": "13833000000",
            "capitalLeaseObligations": "0",
            "longTermDebt": "10272000000",
            "currentLongTermDebt": "4106867218.01",
            "longTermDebtNoncurrent": "None",
            "shortLongTermDebtTotal": "12014000000",
            "otherCurrentLiabilities": "525000000",
            "otherNonCurrentLiabilities": "0",
            "totalShareholderEquity": "9366000000",
            "treasuryStock": "-2071000000",
            "retainedEarnings": "4908000000",
            "commonStock": "767000000",
            "commonStockSharesOutstanding": "721500000"
        },
        {
            "fiscalDateEnding": "2018-09-30",
            "reportedCurrency": "USD",
            "totalAssets": "41859919133.95",
            "totalCurrentAssets": "13714621103.43",
            "cashAndCashEquivalentsAtCarryingValue": "2075127168.38",
            "cashAndShortTermInvestments": "2075127168.38",
            "inventory": "6881439937.39",
            "currentNetReceivables": "None",
            "totalNonCurrentAssets": "0",
            "propertyPlantEquipment": "5527585757.14",
            "accumulatedDepreciationAmortizationPPE": "0",
            "intangibleAssets": "16375374983.70",
            "intangibleAssetsExcludingGoodwill": "16375374983.70",
            "goodwill": "0",
            "investments": "None",
            "longTermInvestments": "4275466284.07",
            "shortTermInvestments": "0",
            "otherCurrentAssets": "123907656.19",
            "otherNonCurrentAssets": "None",
            "totalLiabilities": "27339246119.73",
            "totalCurrentLiabilities": "9296987087.52",
            "currentAccountsPayable": "None",
            "deferredRevenue": "None",
            "currentDebt": "None",
            "shortTermDebt": "0",
            "totalNonCurrentLiabilities": "0",
            "capitalLeaseObligations": "0",
            "longTermDebt": "13598539193.95",
            "currentLongTermDebt": "2021651232.56",
            "longTermDebtNoncurrent": "None",
            "shortLongTermDebtTotal": "None",
            "otherCurrentLiabilities": "1266466675.36",
            "otherNonCurrentLiabilities": "0",
            "totalShareholderEquity": "12215990609.10",
            "treasuryStock": "0",
            "retainedEarnings": "9102647710.97",
            "commonStock": "1000391287.34",
            "commonStockSharesOutstanding": "2508545100"
        },
        {
            "fiscalDateEnding": "2018-06-30",
            "reportedCurrency": "USD",
            "totalAssets": "29715000000",
            "totalCurrentAssets": "8691000000",
            "cashAndCashEquivalentsAtCarryingValue": "874000000",
            "cashAndShortTermInvestments": "874000000",
            "inventory": "5015000000",
            "currentNetReceivables": "None",
            "totalNonCurrentAssets": "21024000000",
            "propertyPlantEquipment": "4112000000",
            "accumulatedDepreciationAmortizationPPE": "0",
            "intangibleAssets": "9894000000",
            "intangibleAssetsExcludingGoodwill": "9894000000",
            "goodwill": "2678000000",
            "investments": "None",
            "longTermInvestments": "9158577801.60",
            "shortTermInvestments": "25000000",
            "otherCurrentAssets": "2777000000",
            "otherNonCurrentAssets": "None",
            "totalLiabilities": "18002000000",
            "totalCurrentLiabilities": "6360000000",
            "currentAccountsPayable": "None",
            "deferredRevenue": "None",
            "currentDebt": "None",
            "shortTermDebt": "1859000000",
            "totalNonCurrentLiabilities": "11642000000",
            "capitalLeaseObligations": "0",
            "longTermDebt": "8074000000",
            "currentLongTermDebt": "4459958896.89",
            "longTermDebtNoncurrent": "None",
            "shortLongTermDebtTotal": "10057000000",
            "otherCurrentLiabilities": "2106000000",
            "otherNonCurrentLiabilities": "0",
            "totalShareholderEquity": "9948000000",
            "treasuryStock": "-2144000000",
            "retainedEarnings": "5686000000",
            "commonStock": "780000000",
            "commonStockSharesOutstanding": "1835491200"
        },
        {
            "fiscalDateEnding": "2018-03-31",
            "reportedCurrency": "USD",
            "totalAssets": "41734550561.80",
            "totalCurrentAssets": "12206460674.16",
            "cashAndCashEquivalentsAtCarryingValue": "1227528089.89",
            "cashAndShortTermInvestments": "1227528089.89",
            "inventory": "7043539325.84",
            "currentNetReceivables": "None",
            "totalNonCurrentAssets": "None",
            "propertyPlantEquipment": "5742977528.09",
            "accumulatedDepreciationAmortizationPPE": "None",
            "intangibleAssets": "13896067415.73",
            "intangibleAssetsExcludingGoodwill": "13896067415.73",
            "goodwill": "3761235955.06",
            "investments": "None",
            "longTermInvestments": "4311797752.81",
            "shortTermInvestments": "35112359.55",
            "otherCurrentAssets": "47752808.99",
            "otherNonCurrentAssets": "None",
            "totalLiabilities": "25283707865.17",
            "totalCurrentLiabilities": "8932584269.66",
            "currentAccountsPayable": "None",
            "deferredRevenue": "None",
            "currentDebt": "None",
            "shortTermDebt": "2099719101.12",
            "totalNonCurrentLiabilities": "None",
            "capitalLeaseObligations": "None",
            "longTermDebt": "11438202247.19",
            "currentLongTermDebt": "2099719101.12",
            "longTermDebtNoncurrent": "None",
            "shortLongTermDebtTotal": "None",
            "otherCurrentLiabilities": "1516853932.58",
            "otherNonCurrentLiabilities": "None",
            "totalShareholderEquity": "13971910112.36",
            "treasuryStock": "0",
            "retainedEarnings": "10997191011.24",
            "commonStock": "1095505617.98",
            "commonStockSharesOutstanding": "2635135400"
        },
        {
            "fiscalDateEnding": "2017-12-31",
            "reportedCurrency": "USD",
            "totalAssets": "30102000000",
            "totalCurrentAssets": "9500000000",
            "cashAndCashEquivalentsAtCarryingValue": "920000000",
            "cashAndShortTermInvestments": "920000000",
            "inventory": "4919000000",
            "currentNetReceivables": "None",
            "totalNonCurrentAssets": "20602000000",
            "propertyPlantEquipment": "3974000000",
            "accumulatedDepreciationAmortizationPPE": "0",
            "intangibleAssets": "12807000000",
            "intangibleAssetsExcludingGoodwill": "12807000000",
            "goodwill": "0",
            "investments": "None",
            "longTermInvestments": "7636435191.07",
            "shortTermInvestments": "123000000",
            "otherCurrentAssets": "409657082.81",
            "otherNonCurrentAssets": "None",
            "totalLiabilities": "18412000000",
            "totalCurrentLiabilities": "7253000000",
            "currentAccountsPayable": "None",
            "deferredRevenue": "None",
            "currentDebt": "None",
            "shortTermDebt": "2378000000",
            "totalNonCurrentLiabilities": "11159000000",
            "capitalLeaseObligations": "0",
            "longTermDebt": "7647000000",
            "currentLongTermDebt": "5278051918.03",
            "longTermDebtNoncurrent": "None",
            "shortLongTermDebtTotal": "10025000000",
            "otherCurrentLiabilities": "433000000",
            "otherNonCurrentLiabilities": "0",
            "totalShareholderEquity": "9922000000",
            "treasuryStock": "-2178000000",
            "retainedEarnings": "5422000000",
            "commonStock": "789000000",
            "commonStockSharesOutstanding": "721500000"
        },
        {
            "fiscalDateEnding": "2017-09-30",
            "reportedCurrency": "USD",
            "totalAssets": "30102000000",
            "totalCurrentAssets": "9500000000",
            "cashAndCashEquivalentsAtCarryingValue": "920000000",
            "cashAndShortTermInvestments": "920000000",
            "inventory": "4919000000",
            "currentNetReceivables": "None",
            "totalNonCurrentAssets": "None",
            "propertyPlantEquipment": "3953000000",
            "accumulatedDepreciationAmortizationPPE": "None",
            "intangibleAssets": "12807000000",
            "intangibleAssetsExcludingGoodwill": "12807000000",
            "goodwill": "None",
            "investments": "None",
            "longTermInvestments": "3102000000",
            "shortTermInvestments": "None",
            "otherCurrentAssets": "123000000",
            "otherNonCurrentAssets": "None",
            "totalLiabilities": "18412000000",
            "totalCurrentLiabilities": "7253000000",
            "currentAccountsPayable": "None",
            "deferredRevenue": "None",
            "currentDebt": "None",
            "shortTermDebt": "2144000000",
            "totalNonCurrentLiabilities": "None",
            "capitalLeaseObligations": "None",
            "longTermDebt": "7647000000",
            "currentLongTermDebt": "2144000000",
            "longTermDebtNoncurrent": "None",
            "shortLongTermDebtTotal": "None",
            "otherCurrentLiabilities": "733000000",
            "otherNonCurrentLiabilities": "None",
            "totalShareholderEquity": "9922000000",
            "treasuryStock": "None",
            "retainedEarnings": "7600000000",
            "commonStock": "789000000",
            "commonStockSharesOutstanding": "1863455300"
        }
    ]
}