{
    "symbol": "AXP",
    "annualReports": [
        {
            "fiscalDateEnding": "2022-12-31",
            "reportedCurrency": "USD",
            "totalAssets": "228354000000",
            "totalCurrentAssets": "33914000000",
            "cashAndCashEquivalentsAtCarryingValue": "33370000000",
            "cashAndShortTermInvestments": "33677000000",
            "inventory": "None",
            "currentNetReceivables": "None",
            "totalNonCurrentAssets": "11584000000",
            "propertyPlantEquipment": "5215000000",
            "accumulatedDepreciationAmortizationPPE": "9850000000",
            "intangibleAssets": "3932000000",
            "intangibleAssetsExcludingGoodwill": "146000000",
            "goodwill": "3786000000",
            "investments": "4790000000",
            "longTermInvestments": "5000000000",
            "shortTermInvestments": "307000000",
            "otherCurrentAssets": "None",
            "otherNonCurrentAssets": "1207000000",
            "totalLiabilities": "203643000000",
            "totalCurrentLiabilities": "3878000000",
            "currentAccountsPayable": "None",
            "deferredRevenue": "None",
            "currentDebt": "1348000000",
            "shortTermDebt": "1348000000",
            "totalNonCurrentLiabilities": "203643000000",
            "capitalLeaseObligations": "3000000",
            "longTermDebt": "42573000000",
            "currentLongTermDebt": "1000000000",
            "longTermDebtNoncurrent": "43000000000",
            "shortLongTermDebtTotal": "43921000000",
            "otherCurrentLiabilities": "-109891000000",
            "otherNonCurrentLiabilities": "37350000000",
            "totalShareholderEquity": "24711000000",
            "treasuryStock": "None",
            "retainedEarnings": "16279000000",
            "commonStock": "149000000",
            "commonStockSharesOutstanding": "743000000"
        },
        {
            "fiscalDateEnding": "2021-12-31",
            "reportedCurrency": "USD",
            "totalAssets": "188548000000",
            "totalCurrentAssets": "22028000000",
            "cashAndCashEquivalentsAtCarryingValue": "21503000000",
            "cashAndShortTermInvestments": "21691000000",
            "inventory": "None",
            "currentNetReceivables": "None",
            "totalNonCurrentAssets": "11253000000",
            "propertyPlantEquipment": "4988000000",
            "accumulatedDepreciationAmortizationPPE": "8602000000",
            "intangibleAssets": "4005000000",
            "intangibleAssetsExcludingGoodwill": "201000000",
            "goodwill": "3804000000",
            "investments": "2805000000",
            "longTermInvestments": "3000000000",
            "shortTermInvestments": "188000000",
            "otherCurrentAssets": "151265000000",
            "otherNonCurrentAssets": "1124000000",
            "totalLiabilities": "166371000000",
            "totalCurrentLiabilities": "4771000000",
            "currentAccountsPayable": "None",
            "deferredRevenue": "None",
            "currentDebt": "2243000000",
            "shortTermDebt": "2243000000",
            "totalNonCurrentLiabilities": "41516000000",
            "capitalLeaseObligations": "14000000",
            "longTermDebt": "38675000000",
            "currentLongTermDebt": "2000000000",
            "longTermDebtNoncurrent": "39000000000",
            "shortLongTermDebtTotal": "40918000000",
            "otherCurrentLiabilities": "-12574000000",
            "otherNonCurrentLiabilities": "30497000000",
            "totalShareholderEquity": "22177000000",
            "treasuryStock": "-271000000",
            "retainedEarnings": "13474000000",
            "commonStock": "153000000",
            "commonStockSharesOutstanding": "761000000"
        },
        {
            "fiscalDateEnding": "2020-12-31",
            "reportedCurrency": "USD",
            "totalAssets": "191000000000",
            "totalCurrentAssets": "32965000000",
            "cashAndCashEquivalentsAtCarryingValue": "32359000000",
            "cashAndShortTermInvestments": "32516000000",
            "inventory": "None",
            "currentNetReceivables": "None",
            "totalNonCurrentAssets": "11438000000",
            "propertyPlantEquipment": "5015000000",
            "accumulatedDepreciationAmortizationPPE": "7540000000",
            "intangibleAssets": "4117000000",
            "intangibleAssetsExcludingGoodwill": "265000000",
            "goodwill": "3852000000",
            "investments": "21662000000",
            "longTermInvestments": "22000000000",
            "shortTermInvestments": "157000000",
            "otherCurrentAssets": "64641000000",
            "otherNonCurrentAssets": "1147000000",
            "totalLiabilities": "168383000000",
            "totalCurrentLiabilities": "4214000000",
            "currentAccountsPayable": "None",
            "deferredRevenue": "None",
            "currentDebt": "1878000000",
            "shortTermDebt": "1878000000",
            "totalNonCurrentLiabilities": "43000000000",
            "capitalLeaseObligations": "17000000",
            "longTermDebt": "42952000000",
            "currentLongTermDebt": "2000000000",
            "longTermDebtNoncurrent": "43000000000",
            "shortLongTermDebtTotal": "44830000000",
            "otherCurrentLiabilities": "-11444000000",
            "otherNonCurrentLiabilities": "27234000000",
            "totalShareholderEquity": "22984000000",
            "treasuryStock": "-279000000",
            "retainedEarnings": "13837000000",
            "commonStock": "161000000",
            "commonStockSharesOutstanding": "805000000"
        },
        {
            "fiscalDateEnding": "2019-12-31",
            "reportedCurrency": "USD",
            "totalAssets": "198000000000",
            "totalCurrentAssets": "23932000000",
            "cashAndCashEquivalentsAtCarryingValue": "23932000000",
            "cashAndShortTermInvestments": "24155000000",
            "inventory": "None",
            "currentNetReceivables": "None",
            "totalNonCurrentAssets": "10791000000",
            "propertyPlantEquipment": "4834000000",
            "accumulatedDepreciationAmortizationPPE": "6562000000",
            "intangibleAssets": "3582000000",
            "intangibleAssetsExcludingGoodwill": "267000000",
            "goodwill": "3315000000",
            "investments": "65887000000",
            "longTermInvestments": "84998000000",
            "shortTermInvestments": "223000000",
            "otherCurrentAssets": "94253000000",
            "otherNonCurrentAssets": "1154000000",
            "totalLiabilities": "175250000000",
            "totalCurrentLiabilities": "8871000000",
            "currentAccountsPayable": "None",
            "deferredRevenue": "None",
            "currentDebt": "6442000000",
            "shortTermDebt": "6442000000",
            "totalNonCurrentLiabilities": "60062000000",
            "capitalLeaseObligations": "25000000",
            "longTermDebt": "57835000000",
            "currentLongTermDebt": "6442000000",
            "longTermDebtNoncurrent": "58000000000",
            "shortLongTermDebtTotal": "64277000000",
            "otherCurrentLiabilities": "-18738000000",
            "otherNonCurrentLiabilities": "24948000000",
            "totalShareholderEquity": "23071000000",
            "treasuryStock": "-292000000",
            "retainedEarnings": "13871000000",
            "commonStock": "163000000",
            "commonStockSharesOutstanding": "810000000"
        },
        {
            "fiscalDateEnding": "2018-12-31",
            "reportedCurrency": "USD",
            "totalAssets": "189000000000",
            "totalCurrentAssets": "27445000000",
            "cashAndCashEquivalentsAtCarryingValue": "27445000000",
            "cashAndShortTermInvestments": "27611000000",
            "inventory": "None",
            "currentNetReceivables": "None",
            "totalNonCurrentAssets": "9929000000",
            "propertyPlantEquipment": "4416000000",
            "accumulatedDepreciationAmortizationPPE": "6015000000",
            "intangibleAssets": "3347000000",
            "intangibleAssetsExcludingGoodwill": "275000000",
            "goodwill": "3072000000",
            "investments": "4995000000",
            "longTermInvestments": "5690000000",
            "shortTermInvestments": "166000000",
            "otherCurrentAssets": "142599000000",
            "otherNonCurrentAssets": "1043000000",
            "totalLiabilities": "166312000000",
            "totalCurrentLiabilities": "5264000000",
            "currentAccountsPayable": "None",
            "deferredRevenue": "743000000",
            "currentDebt": "3100000000",
            "shortTermDebt": "3100000000",
            "totalNonCurrentLiabilities": "60182000000",
            "capitalLeaseObligations": "19000000",
            "longTermDebt": "58423000000",
            "currentLongTermDebt": "4128000000",
            "longTermDebtNoncurrent": "58000000000",
            "shortLongTermDebtTotal": "61523000000",
            "otherCurrentLiabilities": "92553000000",
            "otherNonCurrentLiabilities": "22574000000",
            "totalShareholderEquity": "22290000000",
            "treasuryStock": "-207000000",
            "retainedEarnings": "12499000000",
            "commonStock": "170000000",
            "commonStockSharesOutstanding": "847000000"
        }
    ],
    "quarterlyReports": [
        {
            "fiscalDateEnding": "2023-03-31",
            "reportedCurrency": "USD",
            "totalAssets": "235842000000",
            "totalCurrentAssets": "40836000000",
            "cashAndCashEquivalentsAtCarryingValue": "40287000000",
            "cashAndShortTermInvestments": "40494000000",
            "inventory": "None",
            "currentNetReceivables": "None",
            "totalNonCurrentAssets": "5204000000",
            "propertyPlantEquipment": "5204000000",
            "accumulatedDepreciationAmortizationPPE": "10233000000",
            "intangibleAssets": "None",
            "intangibleAssetsExcludingGoodwill": "None",
            "goodwill": "None",
            "investments": "4050000000",
            "longTermInvestments": "4000000000",
            "shortTermInvestments": "207000000",
            "otherCurrentAssets": "None",
            "otherNonCurrentAssets": "None",
            "totalLiabilities": "209850000000",
            "totalCurrentLiabilities": "1724000000",
            "currentAccountsPayable": "None",
            "deferredRevenue": "None",
            "currentDebt": "1724000000",
            "shortTermDebt": "1724000000",
            "totalNonCurrentLiabilities": "2000000000",
            "capitalLeaseObligations": "None",
            "longTermDebt": "41138000000",
            "currentLongTermDebt": "2000000000",
            "longTermDebtNoncurrent": "41000000000",
            "shortLongTermDebtTotal": "42862000000",
            "otherCurrentLiabilities": "-133332000000",
            "otherNonCurrentLiabilities": "33656000000",
            "totalShareholderEquity": "25992000000",
            "treasuryStock": "None",
            "retainedEarnings": "17427000000",
            "commonStock": "149000000",
            "commonStockSharesOutstanding": "743000000"
        },
        {
            "fiscalDateEnding": "2022-12-31",
            "reportedCurrency": "USD",
            "totalAssets": "228354000000",
            "totalCurrentAssets": "33914000000",
            "cashAndCashEquivalentsAtCarryingValue": "33370000000",
            "cashAndShortTermInvestments": "33677000000",
            "inventory": "None",
            "currentNetReceivables": "None",
            "totalNonCurrentAssets": "11584000000",
            "propertyPlantEquipment": "5215000000",
            "accumulatedDepreciationAmortizationPPE": "9850000000",
            "intangibleAssets": "3932000000",
            "intangibleAssetsExcludingGoodwill": "146000000",
            "goodwill": "3786000000",
            "investments": "4790000000",
            "longTermInvestments": "5000000000",
            "shortTermInvestments": "307000000",
            "otherCurrentAssets": "None",
            "otherNonCurrentAssets": "1207000000",
            "totalLiabilities": "203643000000",
            "totalCurrentLiabilities": "3878000000",
            "currentAccountsPayable": "None",
            "deferredRevenue": "None",
            "currentDebt": "1348000000",
            "shortTermDebt": "1348000000",
            "totalNonCurrentLiabilities": "13133000000",
            "capitalLeaseObligations": "3000000",
            "longTermDebt": "42573000000",
            "currentLongTermDebt": "1000000000",
            "longTermDebtNoncurrent": "43000000000",
            "shortLongTermDebtTotal": "43921000000",
            "otherCurrentLiabilities": "-110239000000",
            "otherNonCurrentLiabilities": "37350000000",
            "totalShareholderEquity": "24711000000",
            "treasuryStock": "None",
            "retainedEarnings": "16279000000",
            "commonStock": "149000000",
            "commonStockSharesOutstanding": "743000000"
        },
        {
            "fiscalDateEnding": "2022-09-30",
            "reportedCurrency": "USD",
            "totalAssets": "214915000000",
            "totalCurrentAssets": "31182000000",
            "cashAndCashEquivalentsAtCarryingValue": "29822000000",
            "cashAndShortTermInvestments": "30825000000",
            "inventory": "None",
            "currentNetReceivables": "None",
            "totalNonCurrentAssets": "5095000000",
            "propertyPlantEquipment": "5095000000",
            "accumulatedDepreciationAmortizationPPE": "9519000000",
            "intangibleAssets": "None",
            "intangibleAssetsExcludingGoodwill": "None",
            "goodwill": "None",
            "investments": "6058000000",
            "longTermInvestments": "5000000000",
            "shortTermInvestments": "1003000000",
            "otherCurrentAssets": "1360000000",
            "otherNonCurrentAssets": "None",
            "totalLiabilities": "190975000000",
            "totalCurrentLiabilities": "1515000000",
            "currentAccountsPayable": "None",
            "deferredRevenue": "None",
            "currentDebt": "1515000000",
            "shortTermDebt": "1515000000",
            "totalNonCurrentLiabilities": "12536000000",
            "capitalLeaseObligations": "None",
            "longTermDebt": "42393000000",
            "currentLongTermDebt": "2000000000",
            "longTermDebtNoncurrent": "42000000000",
            "shortLongTermDebtTotal": "43908000000",
            "otherCurrentLiabilities": "-103948000000",
            "otherNonCurrentLiabilities": "32583000000",
            "totalShareholderEquity": "23940000000",
            "treasuryStock": "None",
            "retainedEarnings": "15685000000",
            "commonStock": "150000000",
            "commonStockSharesOutstanding": "747000000"
        },
        {
            "fiscalDateEnding": "2022-06-30",
            "reportedCurrency": "USD",
            "totalAssets": "205000000000",
            "totalCurrentAssets": "26277000000",
            "cashAndCashEquivalentsAtCarryingValue": "25191000000",
            "cashAndShortTermInvestments": "25873000000",
            "inventory": "None",
            "currentNetReceivables": "None",
            "totalNonCurrentAssets": "5093000000",
            "propertyPlantEquipment": "5093000000",
            "accumulatedDepreciationAmortizationPPE": "9191000000",
            "intangibleAssets": "None",
            "intangibleAssetsExcludingGoodwill": "None",
            "goodwill": "None",
            "investments": "4613000000",
            "longTermInvestments": "4000000000",
            "shortTermInvestments": "682000000",
            "otherCurrentAssets": "-866000000",
            "otherNonCurrentAssets": "None",
            "totalLiabilities": "182063000000",
            "totalCurrentLiabilities": "1984000000",
            "currentAccountsPayable": "None",
            "deferredRevenue": "None",
            "currentDebt": "1984000000",
            "shortTermDebt": "1984000000",
            "totalNonCurrentLiabilities": "13355000000",
            "capitalLeaseObligations": "None",
            "longTermDebt": "40495000000",
            "currentLongTermDebt": "2000000000",
            "longTermDebtNoncurrent": "40000000000",
            "shortLongTermDebtTotal": "42479000000",
            "otherCurrentLiabilities": "-96427000000",
            "otherNonCurrentLiabilities": "31802000000",
            "totalShareholderEquity": "23235000000",
            "treasuryStock": "None",
            "retainedEarnings": "14751000000",
            "commonStock": "151000000",
            "commonStockSharesOutstanding": "751000000"
        },
        {
            "fiscalDateEnding": "2022-03-31",
            "reportedCurrency": "USD",
            "totalAssets": "196000000000",
            "totalCurrentAssets": "27678000000",
            "cashAndCashEquivalentsAtCarryingValue": "25471000000",
            "cashAndShortTermInvestments": "27242000000",
            "inventory": "None",
            "currentNetReceivables": "None",
            "totalNonCurrentAssets": "5046000000",
            "propertyPlantEquipment": "5046000000",
            "accumulatedDepreciationAmortizationPPE": "8907000000",
            "intangibleAssets": "None",
            "intangibleAssetsExcludingGoodwill": "None",
            "goodwill": "None",
            "investments": "4241000000",
            "longTermInvestments": "4000000000",
            "shortTermInvestments": "1771000000",
            "otherCurrentAssets": "2207000000",
            "otherNonCurrentAssets": "None",
            "totalLiabilities": "173479000000",
            "totalCurrentLiabilities": "2122000000",
            "currentAccountsPayable": "None",
            "deferredRevenue": "None",
            "currentDebt": "2122000000",
            "shortTermDebt": "2122000000",
            "totalNonCurrentLiabilities": "13318000000",
            "capitalLeaseObligations": "None",
            "longTermDebt": "38337000000",
            "currentLongTermDebt": "2000000000",
            "longTermDebtNoncurrent": "38000000000",
            "shortLongTermDebtTotal": "40459000000",
            "otherCurrentLiabilities": "122000000",
            "otherNonCurrentLiabilities": "30907000000",
            "totalShareholderEquity": "22383000000",
            "treasuryStock": "None",
            "retainedEarnings": "13754000000",
            "commonStock": "151000000",
            "commonStockSharesOutstanding": "755000000"
        },
        {
            "fiscalDateEnding": "2021-12-31",
            "reportedCurrency": "USD",
            "totalAssets": "188548000000",
            "totalCurrentAssets": "22028000000",
            "cashAndCashEquivalentsAtCarryingValue": "21503000000",
            "cashAndShortTermInvestments": "21691000000",
            "inventory": "None",
            "currentNetReceivables": "None",
            "totalNonCurrentAssets": "11253000000",
            "propertyPlantEquipment": "4988000000",
            "accumulatedDepreciationAmortizationPPE": "8602000000",
            "intangibleAssets": "4005000000",
            "intangibleAssetsExcludingGoodwill": "201000000",
            "goodwill": "3804000000",
            "investments": "2805000000",
            "longTermInvestments": "3000000000",
            "shortTermInvestments": "188000000",
            "otherCurrentAssets": "-20708000000",
            "otherNonCurrentAssets": "1124000000",
            "totalLiabilities": "166371000000",
            "totalCurrentLiabilities": "4771000000",
            "currentAccountsPayable": "None",
            "deferredRevenue": "None",
            "currentDebt": "2243000000",
            "shortTermDebt": "2243000000",
            "totalNonCurrentLiabilities": "12817000000",
            "capitalLeaseObligations": "14000000",
            "longTermDebt": "38675000000",
            "currentLongTermDebt": "2000000000",
            "longTermDebtNoncurrent": "39000000000",
            "shortLongTermDebtTotal": "40918000000",
            "otherCurrentLiabilities": "-12817000000",
            "otherNonCurrentLiabilities": "30497000000",
            "totalShareholderEquity": "22177000000",
            "treasuryStock": "-271000000",
            "retainedEarnings": "13474000000",
            "commonStock": "153000000",
            "commonStockSharesOutstanding": "761000000"
        },
        {
            "fiscalDateEnding": "2021-09-30",
            "reportedCurrency": "USD",
            "totalAssets": "184000000000",
            "totalCurrentAssets": "27916000000",
            "cashAndCashEquivalentsAtCarryingValue": "27441000000",
            "cashAndShortTermInvestments": "27549000000",
            "inventory": "None",
            "currentNetReceivables": "None",
            "totalNonCurrentAssets": "4960000000",
            "propertyPlantEquipment": "4960000000",
            "accumulatedDepreciationAmortizationPPE": "8371000000",
            "intangibleAssets": "None",
            "intangibleAssetsExcludingGoodwill": "None",
            "goodwill": "None",
            "investments": "9487000000",
            "longTermInvestments": "9589000000",
            "shortTermInvestments": "108000000",
            "otherCurrentAssets": "475000000",
            "otherNonCurrentAssets": "None",
            "totalLiabilities": "159835000000",
            "totalCurrentLiabilities": "2253000000",
            "currentAccountsPayable": "None",
            "deferredRevenue": "None",
            "currentDebt": "2253000000",
            "shortTermDebt": "2253000000",
            "totalNonCurrentLiabilities": "34483000000",
            "capitalLeaseObligations": "None",
            "longTermDebt": "34483000000",
            "currentLongTermDebt": "2253000000",
            "longTermDebtNoncurrent": "34000000000",
            "shortLongTermDebtTotal": "36736000000",
            "otherCurrentLiabilities": "84326000000",
            "otherNonCurrentLiabilities": "29132000000",
            "totalShareholderEquity": "24426000000",
            "treasuryStock": "None",
            "retainedEarnings": "14832000000",
            "commonStock": "156000000",
            "commonStockSharesOutstanding": "778000000"
        },
        {
            "fiscalDateEnding": "2021-06-30",
            "reportedCurrency": "USD",
            "totalAssets": "187000000000",
            "totalCurrentAssets": "30796000000",
            "cashAndCashEquivalentsAtCarryingValue": "28955000000",
            "cashAndShortTermInvestments": "30378000000",
            "inventory": "None",
            "currentNetReceivables": "None",
            "totalNonCurrentAssets": "4891000000",
            "propertyPlantEquipment": "4891000000",
            "accumulatedDepreciationAmortizationPPE": "8084000000",
            "intangibleAssets": "None",
            "intangibleAssetsExcludingGoodwill": "None",
            "goodwill": "None",
            "investments": "12392000000",
            "longTermInvestments": "12000000000",
            "shortTermInvestments": "1423000000",
            "otherCurrentAssets": "1841000000",
            "otherNonCurrentAssets": "None",
            "totalLiabilities": "161434000000",
            "totalCurrentLiabilities": "1864000000",
            "currentAccountsPayable": "None",
            "deferredRevenue": "None",
            "currentDebt": "1864000000",
            "shortTermDebt": "1864000000",
            "totalNonCurrentLiabilities": "37363000000",
            "capitalLeaseObligations": "None",
            "longTermDebt": "37363000000",
            "currentLongTermDebt": "2000000000",
            "longTermDebtNoncurrent": "37000000000",
            "shortLongTermDebtTotal": "39227000000",
            "otherCurrentLiabilities": "84905000000",
            "otherNonCurrentLiabilities": "27594000000",
            "totalShareholderEquity": "25539000000",
            "treasuryStock": "None",
            "retainedEarnings": "16402000000",
            "commonStock": "160000000",
            "commonStockSharesOutstanding": "798000000"
        },
        {
            "fiscalDateEnding": "2021-03-31",
            "reportedCurrency": "USD",
            "totalAssets": "193000000000",
            "totalCurrentAssets": "40280000000",
            "cashAndCashEquivalentsAtCarryingValue": "39753000000",
            "cashAndShortTermInvestments": "39966000000",
            "inventory": "None",
            "currentNetReceivables": "None",
            "totalNonCurrentAssets": "4943000000",
            "propertyPlantEquipment": "4943000000",
            "accumulatedDepreciationAmortizationPPE": "7800000000",
            "intangibleAssets": "None",
            "intangibleAssetsExcludingGoodwill": "None",
            "goodwill": "None",
            "investments": "21270000000",
            "longTermInvestments": "21000000000",
            "shortTermInvestments": "213000000",
            "otherCurrentAssets": "-101517000000",
            "otherNonCurrentAssets": "None",
            "totalLiabilities": "168618000000",
            "totalCurrentLiabilities": "1578000000",
            "currentAccountsPayable": "None",
            "deferredRevenue": "None",
            "currentDebt": "1578000000",
            "shortTermDebt": "1578000000",
            "totalNonCurrentLiabilities": "42019000000",
            "capitalLeaseObligations": "None",
            "longTermDebt": "42019000000",
            "currentLongTermDebt": "2000000000",
            "longTermDebtNoncurrent": "42000000000",
            "shortLongTermDebtTotal": "43597000000",
            "otherCurrentLiabilities": "89193000000",
            "otherNonCurrentLiabilities": "27243000000",
            "totalShareholderEquity": "24449000000",
            "treasuryStock": "None",
            "retainedEarnings": "15308000000",
            "commonStock": "161000000",
            "commonStockSharesOutstanding": "803000000"
        },
        {
            "fiscalDateEnding": "2020-12-31",
            "reportedCurrency": "USD",
            "totalAssets": "191000000000",
            "totalCurrentAssets": "32965000000",
            "cashAndCashEquivalentsAtCarryingValue": "32359000000",
            "cashAndShortTermInvestments": "32516000000",
            "inventory": "None",
            "currentNetReceivables": "None",
            "totalNonCurrentAssets": "11438000000",
            "propertyPlantEquipment": "5015000000",
            "accumulatedDepreciationAmortizationPPE": "7540000000",
            "intangibleAssets": "4117000000",
            "intangibleAssetsExcludingGoodwill": "265000000",
            "goodwill": "3852000000",
            "investments": "21662000000",
            "longTermInvestments": "22000000000",
            "shortTermInvestments": "157000000",
            "otherCurrentAssets": "-95853000000",
            "otherNonCurrentAssets": "1147000000",
            "totalLiabilities": "168383000000",
            "totalCurrentLiabilities": "4214000000",
            "currentAccountsPayable": "None",
            "deferredRevenue": "None",
            "currentDebt": "1878000000",
            "shortTermDebt": "1878000000",
            "totalNonCurrentLiabilities": "42952000000",
            "capitalLeaseObligations": "17000000",
            "longTermDebt": "42952000000",
            "currentLongTermDebt": "2000000000",
            "longTermDebtNoncurrent": "43000000000",
            "shortLongTermDebtTotal": "44830000000",
            "otherCurrentLiabilities": "86875000000",
            "otherNonCurrentLiabilities": "27234000000",
            "totalShareholderEquity": "22984000000",
            "treasuryStock": "-279000000",
            "retainedEarnings": "13837000000",
            "commonStock": "161000000",
            "commonStockSharesOutstanding": "805000000"
        },
        {
            "fiscalDateEnding": "2020-09-30",
            "reportedCurrency": "USD",
            "totalAssets": "187000000000",
            "totalCurrentAssets": "33129000000",
            "cashAndCashEquivalentsAtCarryingValue": "33030000000",
            "cashAndShortTermInvestments": "33129000000",
            "inventory": "None",
            "currentNetReceivables": "None",
            "totalNonCurrentAssets": "4835000000",
            "propertyPlantEquipment": "4835000000",
            "accumulatedDepreciationAmortizationPPE": "7470000000",
            "intangibleAssets": "None",
            "intangibleAssetsExcludingGoodwill": "None",
            "goodwill": "None",
            "investments": "63254000000",
            "longTermInvestments": "63918000000",
            "shortTermInvestments": "99000000",
            "otherCurrentAssets": "2597000000",
            "otherNonCurrentAssets": "None",
            "totalLiabilities": "165390000000",
            "totalCurrentLiabilities": "1716000000",
            "currentAccountsPayable": "None",
            "deferredRevenue": "None",
            "currentDebt": "1716000000",
            "shortTermDebt": "1716000000",
            "totalNonCurrentLiabilities": "44777000000",
            "capitalLeaseObligations": "None",
            "longTermDebt": "44777000000",
            "currentLongTermDebt": "1716000000",
            "longTermDebtNoncurrent": "45000000000",
            "shortLongTermDebtTotal": "46493000000",
            "otherCurrentLiabilities": "85461000000",
            "otherNonCurrentLiabilities": "25204000000",
            "totalShareholderEquity": "21869000000",
            "treasuryStock": "None",
            "retainedEarnings": "12762000000",
            "commonStock": "161000000",
            "commonStockSharesOutstanding": "805000000"
        },
        {
            "fiscalDateEnding": "2020-06-30",
            "reportedCurrency": "USD",
            "totalAssets": "189000000000",
            "totalCurrentAssets": "41570000000",
            "cashAndCashEquivalentsAtCarryingValue": "41497000000",
            "cashAndShortTermInvestments": "41570000000",
            "inventory": "None",
            "currentNetReceivables": "None",
            "totalNonCurrentAssets": "4829000000",
            "propertyPlantEquipment": "4829000000",
            "accumulatedDepreciationAmortizationPPE": "7131000000",
            "intangibleAssets": "None",
            "intangibleAssetsExcludingGoodwill": "None",
            "goodwill": "None",
            "investments": "57495000000",
            "longTermInvestments": "64431000000",
            "shortTermInvestments": "73000000",
            "otherCurrentAssets": "606000000",
            "otherNonCurrentAssets": "None",
            "totalLiabilities": "167546000000",
            "totalCurrentLiabilities": "1567000000",
            "currentAccountsPayable": "None",
            "deferredRevenue": "None",
            "currentDebt": "1567000000",
            "shortTermDebt": "1567000000",
            "totalNonCurrentLiabilities": "48797000000",
            "capitalLeaseObligations": "None",
            "longTermDebt": "48797000000",
            "currentLongTermDebt": "1567000000",
            "longTermDebtNoncurrent": "49000000000",
            "shortLongTermDebtTotal": "50364000000",
            "otherCurrentLiabilities": "84805000000",
            "otherNonCurrentLiabilities": "24646000000",
            "totalShareholderEquity": "21062000000",
            "treasuryStock": "None",
            "retainedEarnings": "12052000000",
            "commonStock": "161000000",
            "commonStockSharesOutstanding": "805000000"
        },
        {
            "fiscalDateEnding": "2020-03-31",
            "reportedCurrency": "USD",
            "totalAssets": "186000000000",
            "totalCurrentAssets": "36170000000",
            "cashAndCashEquivalentsAtCarryingValue": "36095000000",
            "cashAndShortTermInvestments": "36170000000",
            "inventory": "None",
            "currentNetReceivables": "None",
            "totalNonCurrentAssets": "4798000000",
            "propertyPlantEquipment": "4798000000",
            "accumulatedDepreciationAmortizationPPE": "6799000000",
            "intangibleAssets": "None",
            "intangibleAssetsExcludingGoodwill": "None",
            "goodwill": "None",
            "investments": "49760000000",
            "longTermInvestments": "72464000000",
            "shortTermInvestments": "75000000",
            "otherCurrentAssets": "2513000000",
            "otherNonCurrentAssets": "None",
            "totalLiabilities": "165054000000",
            "totalCurrentLiabilities": "3497000000",
            "currentAccountsPayable": "None",
            "deferredRevenue": "None",
            "currentDebt": "3497000000",
            "shortTermDebt": "3497000000",
            "totalNonCurrentLiabilities": "52588000000",
            "capitalLeaseObligations": "None",
            "longTermDebt": "52588000000",
            "currentLongTermDebt": "3497000000",
            "longTermDebtNoncurrent": "None",
            "shortLongTermDebtTotal": "56085000000",
            "otherCurrentLiabilities": "77962000000",
            "otherNonCurrentLiabilities": "23030000000",
            "totalShareholderEquity": "21006000000",
            "treasuryStock": "None",
            "retainedEarnings": "12161000000",
            "commonStock": "161000000",
            "commonStockSharesOutstanding": "805000000"
        },
        {
            "fiscalDateEnding": "2019-12-31",
            "reportedCurrency": "USD",
            "totalAssets": "198000000000",
            "totalCurrentAssets": "23932000000",
            "cashAndCashEquivalentsAtCarryingValue": "23932000000",
            "cashAndShortTermInvestments": "24155000000",
            "inventory": "None",
            "currentNetReceivables": "None",
            "totalNonCurrentAssets": "10791000000",
            "propertyPlantEquipment": "4834000000",
            "accumulatedDepreciationAmortizationPPE": "6562000000",
            "intangibleAssets": "3582000000",
            "intangibleAssetsExcludingGoodwill": "267000000",
            "goodwill": "3315000000",
            "investments": "65887000000",
            "longTermInvestments": "84998000000",
            "shortTermInvestments": "223000000",
            "otherCurrentAssets": "514000000",
            "otherNonCurrentAssets": "1154000000",
            "totalLiabilities": "175250000000",
            "totalCurrentLiabilities": "8871000000",
            "currentAccountsPayable": "None",
            "deferredRevenue": "None",
            "currentDebt": "6442000000",
            "shortTermDebt": "6442000000",
            "totalNonCurrentLiabilities": "59897000000",
            "capitalLeaseObligations": "25000000",
            "longTermDebt": "57835000000",
            "currentLongTermDebt": "6442000000",
            "longTermDebtNoncurrent": "58000000000",
            "shortLongTermDebtTotal": "64277000000",
            "otherCurrentLiabilities": "73287000000",
            "otherNonCurrentLiabilities": "24948000000",
            "totalShareholderEquity": "23071000000",
            "treasuryStock": "None",
            "retainedEarnings": "13871000000",
            "commonStock": "163000000",
            "commonStockSharesOutstanding": "810000000"
        },
        {
            "fiscalDateEnding": "2019-09-30",
            "reportedCurrency": "USD",
            "totalAssets": "194000000000",
            "totalCurrentAssets": "24341000000",
            "cashAndCashEquivalentsAtCarryingValue": "24266000000",
            "cashAndShortTermInvestments": "24341000000",
            "inventory": "None",
            "currentNetReceivables": "None",
            "totalNonCurrentAssets": "4715000000",
            "propertyPlantEquipment": "4715000000",
            "accumulatedDepreciationAmortizationPPE": "6681000000",
            "intangibleAssets": "None",
            "intangibleAssetsExcludingGoodwill": "None",
            "goodwill": "None",
            "investments": "65070000000",
            "longTermInvestments": "8445000000",
            "shortTermInvestments": "75000000",
            "otherCurrentAssets": "1088000000",
            "otherNonCurrentAssets": "None",
            "totalLiabilities": "171159000000",
            "totalCurrentLiabilities": "2818000000",
            "currentAccountsPayable": "None",
            "deferredRevenue": "None",
            "currentDebt": "2818000000",
            "shortTermDebt": "2818000000",
            "totalNonCurrentLiabilities": "58474000000",
            "capitalLeaseObligations": "None",
            "longTermDebt": "58474000000",
            "currentLongTermDebt": "2818000000",
            "longTermDebtNoncurrent": "None",
            "shortLongTermDebtTotal": "61292000000",
            "otherCurrentLiabilities": "73298000000",
            "otherNonCurrentLiabilities": "23703000000",
            "totalShareholderEquity": "23025000000",
            "treasuryStock": "None",
            "retainedEarnings": "13652000000",
            "commonStock": "165000000",
            "commonStockSharesOutstanding": "821000000"
        },
        {
            "fiscalDateEnding": "2019-06-30",
            "reportedCurrency": "USD",
            "totalAssets": "198000000000",
            "totalCurrentAssets": "26954000000",
            "cashAndCashEquivalentsAtCarryingValue": "26869000000",
            "cashAndShortTermInvestments": "26954000000",
            "inventory": "None",
            "currentNetReceivables": "None",
            "totalNonCurrentAssets": "4658000000",
            "propertyPlantEquipment": "4658000000",
            "accumulatedDepreciationAmortizationPPE": "6581000000",
            "intangibleAssets": "None",
            "intangibleAssetsExcludingGoodwill": "None",
            "goodwill": "None",
            "investments": "67250000000",
            "longTermInvestments": "8542000000",
            "shortTermInvestments": "85000000",
            "otherCurrentAssets": "463000000",
            "otherNonCurrentAssets": "None",
            "totalLiabilities": "174511000000",
            "totalCurrentLiabilities": "3540000000",
            "currentAccountsPayable": "None",
            "deferredRevenue": "713000000",
            "currentDebt": "2827000000",
            "shortTermDebt": "2827000000",
            "totalNonCurrentLiabilities": "57736000000",
            "capitalLeaseObligations": "None",
            "longTermDebt": "57736000000",
            "currentLongTermDebt": "2827000000",
            "longTermDebtNoncurrent": "None",
            "shortLongTermDebtTotal": "60563000000",
            "otherCurrentLiabilities": "72590000000",
            "otherNonCurrentLiabilities": "24840000000",
            "totalShareholderEquity": "23092000000",
            "treasuryStock": "None",
            "retainedEarnings": "13551000000",
            "commonStock": "167000000",
            "commonStockSharesOutstanding": "832000000"
        },
        {
            "fiscalDateEnding": "2019-03-31",
            "reportedCurrency": "USD",
            "totalAssets": "197000000000",
            "totalCurrentAssets": "33177000000",
            "cashAndCashEquivalentsAtCarryingValue": "33177000000",
            "cashAndShortTermInvestments": "33177000000",
            "inventory": "None",
            "currentNetReceivables": "None",
            "totalNonCurrentAssets": "4479000000",
            "propertyPlantEquipment": "4479000000",
            "accumulatedDepreciationAmortizationPPE": "6315000000",
            "intangibleAssets": "None",
            "intangibleAssetsExcludingGoodwill": "None",
            "goodwill": "None",
            "investments": "6410000000",
            "longTermInvestments": "78874000000",
            "shortTermInvestments": "4600000000",
            "otherCurrentAssets": "454000000",
            "otherNonCurrentAssets": "None",
            "totalLiabilities": "174975000000",
            "totalCurrentLiabilities": "2028000000",
            "currentAccountsPayable": "None",
            "deferredRevenue": "None",
            "currentDebt": "2028000000",
            "shortTermDebt": "2028000000",
            "totalNonCurrentLiabilities": "58418000000",
            "capitalLeaseObligations": "None",
            "longTermDebt": "58418000000",
            "currentLongTermDebt": "2028000000",
            "longTermDebtNoncurrent": "None",
            "shortLongTermDebtTotal": "60446000000",
            "otherCurrentLiabilities": "72857000000",
            "otherNonCurrentLiabilities": "25510000000",
            "totalShareholderEquity": "22218000000",
            "treasuryStock": "None",
            "retainedEarnings": "12686000000",
            "commonStock": "168000000",
            "commonStockSharesOutstanding": "837000000"
        },
        {
            "fiscalDateEnding": "2018-12-31",
            "reportedCurrency": "USD",
            "totalAssets": "189000000000",
            "totalCurrentAssets": "27445000000",
            "cashAndCashEquivalentsAtCarryingValue": "27445000000",
            "cashAndShortTermInvestments": "27611000000",
            "inventory": "None",
            "currentNetReceivables": "None",
            "totalNonCurrentAssets": "9929000000",
            "propertyPlantEquipment": "4416000000",
            "accumulatedDepreciationAmortizationPPE": "6015000000",
            "intangibleAssets": "3347000000",
            "intangibleAssetsExcludingGoodwill": "275000000",
            "goodwill": "3072000000",
            "investments": "4995000000",
            "longTermInvestments": "79720000000",
            "shortTermInvestments": "166000000",
            "otherCurrentAssets": "1821000000",
            "otherNonCurrentAssets": "1043000000",
            "totalLiabilities": "166312000000",
            "totalCurrentLiabilities": "5264000000",
            "currentAccountsPayable": "None",
            "deferredRevenue": "743000000",
            "currentDebt": "3100000000",
            "shortTermDebt": "3100000000",
            "totalNonCurrentLiabilities": "60182000000",
            "capitalLeaseObligations": "None",
            "longTermDebt": "58423000000",
            "currentLongTermDebt": "None",
            "longTermDebtNoncurrent": "58000000000",
            "shortLongTermDebtTotal": "61523000000",
            "otherCurrentLiabilities": "69960000000",
            "otherNonCurrentLiabilities": "22574000000",
            "totalShareholderEquity": "22290000000",
            "treasuryStock": "None",
            "retainedEarnings": "12499000000",
            "commonStock": "170000000",
            "commonStockSharesOutstanding": "847000000"
        },
        {
            "fiscalDateEnding": "2018-09-30",
            "reportedCurrency": "USD",
            "totalAssets": "189000000000",
            "totalCurrentAssets": "30231000000",
            "cashAndCashEquivalentsAtCarryingValue": "30231000000",
            "cashAndShortTermInvestments": "30231000000",
            "inventory": "None",
            "currentNetReceivables": "None",
            "totalNonCurrentAssets": "4295000000",
            "propertyPlantEquipment": "4295000000",
            "accumulatedDepreciationAmortizationPPE": "6116000000",
            "intangibleAssets": "None",
            "intangibleAssetsExcludingGoodwill": "None",
            "goodwill": "None",
            "investments": "6071000000",
            "longTermInvestments": "75666000000",
            "shortTermInvestments": "3612000000",
            "otherCurrentAssets": "1032000000",
            "otherNonCurrentAssets": "None",
            "totalLiabilities": "167632000000",
            "totalCurrentLiabilities": "2949000000",
            "currentAccountsPayable": "None",
            "deferredRevenue": "None",
            "currentDebt": "2292000000",
            "shortTermDebt": "2292000000",
            "totalNonCurrentLiabilities": "55300000000",
            "capitalLeaseObligations": "None",
            "longTermDebt": "55300000000",
            "currentLongTermDebt": "57000000000",
            "longTermDebtNoncurrent": "None",
            "shortLongTermDebtTotal": "57592000000",
            "otherCurrentLiabilities": "69301000000",
            "otherNonCurrentLiabilities": "25134000000",
            "totalShareholderEquity": "21460000000",
            "treasuryStock": "None",
            "retainedEarnings": "11521000000",
            "commonStock": "171000000",
            "commonStockSharesOutstanding": "854000000"
        },
        {
            "fiscalDateEnding": "2018-06-30",
            "reportedCurrency": "USD",
            "totalAssets": "185000000000",
            "totalCurrentAssets": "29743000000",
            "cashAndCashEquivalentsAtCarryingValue": "29743000000",
            "cashAndShortTermInvestments": "29743000000",
            "inventory": "None",
            "currentNetReceivables": "None",
            "totalNonCurrentAssets": "4251000000",
            "propertyPlantEquipment": "4251000000",
            "accumulatedDepreciationAmortizationPPE": "5917000000",
            "intangibleAssets": "None",
            "intangibleAssetsExcludingGoodwill": "None",
            "goodwill": "None",
            "investments": "4753000000",
            "longTermInvestments": "73579000000",
            "shortTermInvestments": "1787000000",
            "otherCurrentAssets": "1263000000",
            "otherNonCurrentAssets": "None",
            "totalLiabilities": "163969000000",
            "totalCurrentLiabilities": "2645000000",
            "currentAccountsPayable": "None",
            "deferredRevenue": "None",
            "currentDebt": "1972000000",
            "shortTermDebt": "1972000000",
            "totalNonCurrentLiabilities": "55883000000",
            "capitalLeaseObligations": "None",
            "longTermDebt": "55883000000",
            "currentLongTermDebt": "57898000000",
            "longTermDebtNoncurrent": "None",
            "shortLongTermDebtTotal": "57855000000",
            "otherCurrentLiabilities": "67391000000",
            "otherNonCurrentLiabilities": "24923000000",
            "totalShareholderEquity": "20892000000",
            "treasuryStock": "None",
            "retainedEarnings": "10896000000",
            "commonStock": "173000000",
            "commonStockSharesOutstanding": "861000000"
        }
    ]
}